MANIFEST.in
README.rst
requirements-install.txt
requirements-test.txt
setup.py
best_log_formatter/__init__.py
best_log_formatter/formatter.py
best_log_formatter.egg-info/PKG-INFO
best_log_formatter.egg-info/SOURCES.txt
best_log_formatter.egg-info/dependency_links.txt
best_log_formatter.egg-info/top_level.txt