Metadata-Version: 1.1
Name: best-log-formatter
Version: 0.1
Summary: A pretty cool log formatter.
Home-page: https://github.com/cardforcoin/best-python-log-formatter
Author: Chris Martin
Author-email: ch.martin@gmail.com
License: MIT
Platform: UNKNOWN
Classifier: Intended Audience :: Developers
Classifier: License :: OSI Approved :: MIT License
Classifier: Programming Language :: Python
Classifier: Topic :: Software Development :: Libraries :: Python Modules
Classifier: Programming Language :: Python :: 2.7
Classifier: Programming Language :: Python :: 3.3
Classifier: Programming Language :: Python :: 3.4
